milanesas/__init__.py
milanesas/eda_helper.py
milanesas-0.1.33.dist-info/LICENSE
milanesas-0.1.33.dist-info/METADATA
milanesas-0.1.33.dist-info/WHEEL
milanesas-0.1.33.dist-info/RECORD
