Metadata-Version: 2.1
Name: milanesas
Version: 0.1.33
Summary: A group of tools to do exploratory analysis.
Home-page: https://torrezmn.github.io/EDA_Helper/eda_helper/
Keywords: packaging,data_science,pandas
Author: Torrez, Milton
Author-email: torrez.mn@gmail.com
Requires-Python: >=3.9,<4.0
Classifier: Programming Language :: Python :: 3
Classifier: Programming Language :: Python :: 3.9
Classifier: Programming Language :: Python :: 3.10
Classifier: Programming Language :: Python :: 3.11
Classifier: Programming Language :: Python :: 3.12
Requires-Dist: matplotlib (>=3.5,<4.0)
Requires-Dist: numpy (>=1.23.4,<2.0.0)
Requires-Dist: pandas (>=1.5.3,<2.0.0)
